arcane/facebook/__init__.py
arcane/facebook/exceptions.py
arcane/facebook/facebook.py
arcane_facebook-1.6.0.dist-info/METADATA
arcane_facebook-1.6.0.dist-info/WHEEL
arcane_facebook-1.6.0.dist-info/RECORD
