Metadata-Version: 2.3
Name: arcane-facebook
Version: 1.6.0
Summary: Helpers to request facebook API
Author: Arcane
Author-email: product@wearcane.com
Requires-Python: >=3.9,<4.0
Classifier: Programming Language :: Python :: 3
Classifier: Programming Language :: Python :: 3.9
Classifier: Programming Language :: Python :: 3.10
Classifier: Programming Language :: Python :: 3.11
Classifier: Programming Language :: Python :: 3.12
Classifier: Programming Language :: Python :: 3.13
Requires-Dist: arcane-pubsub (>=1.1.0,<2.0.0)
Requires-Dist: backoff (>=1.10.0)
Requires-Dist: facebook_business (==23.0.1)
Requires-Dist: typing-extensions (>=3.7)
